clickupy/__init__.py
clickupy/fuse.py
clickupy/handler.py
clickupy-0.0.4.data/scripts/clickup
clickupy-0.0.4.dist-info/METADATA
clickupy-0.0.4.dist-info/RECORD
clickupy-0.0.4.dist-info/WHEEL
clickupy-0.0.4.dist-info/top_level.txt
