Metadata-Version: 2.1
Name: clickupy
Version: 0.0.4
Summary: Package for interacting with the clickup api
Home-page: https://github.com/dang3r/clickupy
Author: Daniel Cardoza
Author-email: dan@danielcardoza.com
License: MIT
Platform: UNKNOWN
Requires-Python: >=3.4.0
Requires-Dist: click
Requires-Dist: requests
